arcgis/map/.npmrc
arcgis/map/__init__.py
arcgis/map/_utils.py
arcgis/map/forms.py
arcgis/map/group_layer.py
arcgis/map/map_widget.py
arcgis/map/offline_mapping.py
arcgis/map/popups.py
arcgis/map/renderers.py
arcgis/map/scene_widget.py
arcgis/map/smart_mapping.py
arcgis/map/symbols.py
arcgis/map/tsconfig.json
arcgis/map/dataclasses/__init__.py
arcgis/map/dataclasses/enums/__init__.py
arcgis/map/dataclasses/enums/forms.py
arcgis/map/dataclasses/enums/layer_definition.py
arcgis/map/dataclasses/enums/layers.py
arcgis/map/dataclasses/enums/link_charts.py
arcgis/map/dataclasses/enums/mapping.py
arcgis/map/dataclasses/enums/popups.py
arcgis/map/dataclasses/enums/renderers.py
arcgis/map/dataclasses/enums/symbols.py
arcgis/map/dataclasses/models/__init__.py
arcgis/map/dataclasses/models/base_model.py
arcgis/map/dataclasses/models/forms.py
arcgis/map/dataclasses/models/geometry.py
arcgis/map/dataclasses/models/layer_definition.py
arcgis/map/dataclasses/models/layers.py
arcgis/map/dataclasses/models/link_charts.py
arcgis/map/dataclasses/models/mapping.py
arcgis/map/dataclasses/models/popups.py
arcgis/map/dataclasses/models/renderers.py
arcgis/map/dataclasses/models/symbols.py
arcgis/map/definitions/_3d_basemap_definitions.py
arcgis/map/definitions/__init__.py
arcgis/map/definitions/_basemap_definitions.py
arcgis/map/definitions/_renderer_metaclass.py
arcgis/map/static/map_widget.css
arcgis/map/static/map_widget.js
arcgis/map/static/scene_widget.css
arcgis/map/static/scene_widget.js
arcgis_mapping-4.31.0.dist-info/METADATA
arcgis_mapping-4.31.0.dist-info/WHEEL
arcgis_mapping-4.31.0.dist-info/RECORD
